{"nodes": [{"id": "apps_web_src_app_dashboard_customers_page_tsx", "label": "page.tsx", "file_type": "code", "source_file": "apps\\web\\src\\app\\dashboard\\customers\\page.tsx", "source_location": "L1"}, {"id": "page_fetchcustomers", "label": "fetchCustomers()", "file_type": "code", "source_file": "apps\\web\\src\\app\\dashboard\\customers\\page.tsx", "source_location": "L71"}, {"id": "page_handlepanvalidation", "label": "handlePanValidation()", "file_type": "code", "source_file": "apps\\web\\src\\app\\dashboard\\customers\\page.tsx", "source_location": "L85"}, {"id": "page_handleaddcustomer", "label": "handleAddCustomer()", "file_type": "code", "source_file": "apps\\web\\src\\app\\dashboard\\customers\\page.tsx", "source_location": "L94"}, {"id": "page_handlestartedit", "label": "handleStartEdit()", "file_type": "code", "source_file": "apps\\web\\src\\app\\dashboard\\customers\\page.tsx", "source_location": "L114"}, {"id": "page_handlesaveedit", "label": "handleSaveEdit()", "file_type": "code", "source_file": "apps\\web\\src\\app\\dashboard\\customers\\page.tsx", "source_location": "L123"}, {"id": "page_handleaddcontact", "label": "handleAddContact()", "file_type": "code", "source_file": "apps\\web\\src\\app\\dashboard\\customers\\page.tsx", "source_location": "L146"}, {"id": "page_togglecustomeractivestate", "label": "toggleCustomerActiveState()", "file_type": "code", "source_file": "apps\\web\\src\\app\\dashboard\\customers\\page.tsx", "source_location": "L168"}, {"id": "page_handleloadtimeline", "label": "handleLoadTimeline()", "file_type": "code", "source_file": "apps\\web\\src\\app\\dashboard\\customers\\page.tsx", "source_location": "L179"}], "edges": [{"source": "apps_web_src_app_dashboard_customers_page_tsx", "target": "react", "relation": "imports_from", "confidence": "EXTRACTED", "source_file": "apps\\web\\src\\app\\dashboard\\customers\\page.tsx", "source_location": "L3", "weight": 1.0}, {"source": "apps_web_src_app_dashboard_customers_page_tsx", "target": "lucide_react", "relation": "imports_from", "confidence": "EXTRACTED", "source_file": "apps\\web\\src\\app\\dashboard\\customers\\page.tsx", "source_location": "L4", "weight": 1.0}, {"source": "apps_web_src_app_dashboard_customers_page_tsx", "target": "apps_web_src_lib_api", "relation": "imports_from", "confidence": "EXTRACTED", "source_file": "apps\\web\\src\\app\\dashboard\\customers\\page.tsx", "source_location": "L19", "weight": 1.0}, {"source": "apps_web_src_app_dashboard_customers_page_tsx", "target": "page_fetchcustomers", "relation": "contains", "confidence": "EXTRACTED", "source_file": "apps\\web\\src\\app\\dashboard\\customers\\page.tsx", "source_location": "L71", "weight": 1.0}, {"source": "apps_web_src_app_dashboard_customers_page_tsx", "target": "page_handlepanvalidation", "relation": "contains", "confidence": "EXTRACTED", "source_file": "apps\\web\\src\\app\\dashboard\\customers\\page.tsx", "source_location": "L85", "weight": 1.0}, {"source": "apps_web_src_app_dashboard_customers_page_tsx", "target": "page_handleaddcustomer", "relation": "contains", "confidence": "EXTRACTED", "source_file": "apps\\web\\src\\app\\dashboard\\customers\\page.tsx", "source_location": "L94", "weight": 1.0}, {"source": "apps_web_src_app_dashboard_customers_page_tsx", "target": "page_handlestartedit", "relation": "contains", "confidence": "EXTRACTED", "source_file": "apps\\web\\src\\app\\dashboard\\customers\\page.tsx", "source_location": "L114", "weight": 1.0}, {"source": "apps_web_src_app_dashboard_customers_page_tsx", "target": "page_handlesaveedit", "relation": "contains", "confidence": "EXTRACTED", "source_file": "apps\\web\\src\\app\\dashboard\\customers\\page.tsx", "source_location": "L123", "weight": 1.0}, {"source": "apps_web_src_app_dashboard_customers_page_tsx", "target": "page_handleaddcontact", "relation": "contains", "confidence": "EXTRACTED", "source_file": "apps\\web\\src\\app\\dashboard\\customers\\page.tsx", "source_location": "L146", "weight": 1.0}, {"source": "apps_web_src_app_dashboard_customers_page_tsx", "target": "page_togglecustomeractivestate", "relation": "contains", "confidence": "EXTRACTED", "source_file": "apps\\web\\src\\app\\dashboard\\customers\\page.tsx", "source_location": "L168", "weight": 1.0}, {"source": "apps_web_src_app_dashboard_customers_page_tsx", "target": "page_handleloadtimeline", "relation": "contains", "confidence": "EXTRACTED", "source_file": "apps\\web\\src\\app\\dashboard\\customers\\page.tsx", "source_location": "L179", "weight": 1.0}, {"source": "page_handleaddcustomer", "target": "page_fetchcustomers", "relation": "calls", "confidence": "EXTRACTED", "source_file": "apps\\web\\src\\app\\dashboard\\customers\\page.tsx", "source_location": "L107", "weight": 1.0}, {"source": "page_handlesaveedit", "target": "page_fetchcustomers", "relation": "calls", "confidence": "EXTRACTED", "source_file": "apps\\web\\src\\app\\dashboard\\customers\\page.tsx", "source_location": "L139", "weight": 1.0}, {"source": "page_handleaddcontact", "target": "page_fetchcustomers", "relation": "calls", "confidence": "EXTRACTED", "source_file": "apps\\web\\src\\app\\dashboard\\customers\\page.tsx", "source_location": "L161", "weight": 1.0}, {"source": "page_togglecustomeractivestate", "target": "page_fetchcustomers", "relation": "calls", "confidence": "EXTRACTED", "source_file": "apps\\web\\src\\app\\dashboard\\customers\\page.tsx", "source_location": "L173", "weight": 1.0}], "raw_calls": [{"caller_nid": "page_fetchcustomers", "callee": "setLoading", "source_file": "apps\\web\\src\\app\\dashboard\\customers\\page.tsx", "source_location": "L73"}, {"caller_nid": "page_fetchcustomers", "callee": "get", "source_file": "apps\\web\\src\\app\\dashboard\\customers\\page.tsx", "source_location": "L74"}, {"caller_nid": "page_fetchcustomers", "callee": "setCustomers", "source_file": "apps\\web\\src\\app\\dashboard\\customers\\page.tsx", "source_location": "L75"}, {"caller_nid": "page_fetchcustomers", "callee": "alert", "source_file": "apps\\web\\src\\app\\dashboard\\customers\\page.tsx", "source_location": "L77"}, {"caller_nid": "page_fetchcustomers", "callee": "setLoading", "source_file": "apps\\web\\src\\app\\dashboard\\customers\\page.tsx", "source_location": "L79"}, {"caller_nid": "page_handlepanvalidation", "callee": "setCustPan", "source_file": "apps\\web\\src\\app\\dashboard\\customers\\page.tsx", "source_location": "L86"}, {"caller_nid": "page_handlepanvalidation", "callee": "test", "source_file": "apps\\web\\src\\app\\dashboard\\customers\\page.tsx", "source_location": "L87"}, {"caller_nid": "page_handlepanvalidation", "callee": "setPanError", "source_file": "apps\\web\\src\\app\\dashboard\\customers\\page.tsx", "source_location": "L88"}, {"caller_nid": "page_handlepanvalidation", "callee": "setPanError", "source_file": "apps\\web\\src\\app\\dashboard\\customers\\page.tsx", "source_location": "L90"}, {"caller_nid": "page_handleaddcustomer", "callee": "preventDefault", "source_file": "apps\\web\\src\\app\\dashboard\\customers\\page.tsx", "source_location": "L95"}, {"caller_nid": "page_handleaddcustomer", "callee": "test", "source_file": "apps\\web\\src\\app\\dashboard\\customers\\page.tsx", "source_location": "L97"}, {"caller_nid": "page_handleaddcustomer", "callee": "setPanError", "source_file": "apps\\web\\src\\app\\dashboard\\customers\\page.tsx", "source_location": "L98"}, {"caller_nid": "page_handleaddcustomer", "callee": "post", "source_file": "apps\\web\\src\\app\\dashboard\\customers\\page.tsx", "source_location": "L103"}, {"caller_nid": "page_handleaddcustomer", "callee": "setCustName", "source_file": "apps\\web\\src\\app\\dashboard\\customers\\page.tsx", "source_location": "L104"}, {"caller_nid": "page_handleaddcustomer", "callee": "setCustPan", "source_file": "apps\\web\\src\\app\\dashboard\\customers\\page.tsx", "source_location": "L105"}, {"caller_nid": "page_handleaddcustomer", "callee": "setActivePanel", "source_file": "apps\\web\\src\\app\\dashboard\\customers\\page.tsx", "source_location": "L106"}, {"caller_nid": "page_handleaddcustomer", "callee": "alert", "source_file": "apps\\web\\src\\app\\dashboard\\customers\\page.tsx", "source_location": "L108"}, {"caller_nid": "page_handleaddcustomer", "callee": "alert", "source_file": "apps\\web\\src\\app\\dashboard\\customers\\page.tsx", "source_location": "L110"}, {"caller_nid": "page_handlestartedit", "callee": "setActiveCustId", "source_file": "apps\\web\\src\\app\\dashboard\\customers\\page.tsx", "source_location": "L115"}, {"caller_nid": "page_handlestartedit", "callee": "setCustName", "source_file": "apps\\web\\src\\app\\dashboard\\customers\\page.tsx", "source_location": "L116"}, {"caller_nid": "page_handlestartedit", "callee": "setCustPan", "source_file": "apps\\web\\src\\app\\dashboard\\customers\\page.tsx", "source_location": "L117"}, {"caller_nid": "page_handlestartedit", "callee": "setCustActive", "source_file": "apps\\web\\src\\app\\dashboard\\customers\\page.tsx", "source_location": "L118"}, {"caller_nid": "page_handlestartedit", "callee": "setPanError", "source_file": "apps\\web\\src\\app\\dashboard\\customers\\page.tsx", "source_location": "L119"}, {"caller_nid": "page_handlestartedit", "callee": "setActivePanel", "source_file": "apps\\web\\src\\app\\dashboard\\customers\\page.tsx", "source_location": "L120"}, {"caller_nid": "page_handlesaveedit", "callee": "preventDefault", "source_file": "apps\\web\\src\\app\\dashboard\\customers\\page.tsx", "source_location": "L124"}, {"caller_nid": "page_handlesaveedit", "callee": "test", "source_file": "apps\\web\\src\\app\\dashboard\\customers\\page.tsx", "source_location": "L126"}, {"caller_nid": "page_handlesaveedit", "callee": "setPanError", "source_file": "apps\\web\\src\\app\\dashboard\\customers\\page.tsx", "source_location": "L127"}, {"caller_nid": "page_handlesaveedit", "callee": "patch", "source_file": "apps\\web\\src\\app\\dashboard\\customers\\page.tsx", "source_location": "L132"}, {"caller_nid": "page_handlesaveedit", "callee": "find", "source_file": "apps\\web\\src\\app\\dashboard\\customers\\page.tsx", "source_location": "L133"}, {"caller_nid": "page_handlesaveedit", "callee": "patch", "source_file": "apps\\web\\src\\app\\dashboard\\customers\\page.tsx", "source_location": "L135"}, {"caller_nid": "page_handlesaveedit", "callee": "setActivePanel", "source_file": "apps\\web\\src\\app\\dashboard\\customers\\page.tsx", "source_location": "L137"}, {"caller_nid": "page_handlesaveedit", "callee": "setActiveCustId", "source_file": "apps\\web\\src\\app\\dashboard\\customers\\page.tsx", "source_location": "L138"}, {"caller_nid": "page_handlesaveedit", "callee": "alert", "source_file": "apps\\web\\src\\app\\dashboard\\customers\\page.tsx", "source_location": "L140"}, {"caller_nid": "page_handlesaveedit", "callee": "alert", "source_file": "apps\\web\\src\\app\\dashboard\\customers\\page.tsx", "source_location": "L142"}, {"caller_nid": "page_handleaddcontact", "callee": "preventDefault", "source_file": "apps\\web\\src\\app\\dashboard\\customers\\page.tsx", "source_location": "L147"}, {"caller_nid": "page_handleaddcontact", "callee": "post", "source_file": "apps\\web\\src\\app\\dashboard\\customers\\page.tsx", "source_location": "L151"}, {"caller_nid": "page_handleaddcontact", "callee": "setContactName", "source_file": "apps\\web\\src\\app\\dashboard\\customers\\page.tsx", "source_location": "L157"}, {"caller_nid": "page_handleaddcontact", "callee": "setContactEmail", "source_file": "apps\\web\\src\\app\\dashboard\\customers\\page.tsx", "source_location": "L158"}, {"caller_nid": "page_handleaddcontact", "callee": "setContactPhone", "source_file": "apps\\web\\src\\app\\dashboard\\customers\\page.tsx", "source_location": "L159"}, {"caller_nid": "page_handleaddcontact", "callee": "setContactRole", "source_file": "apps\\web\\src\\app\\dashboard\\customers\\page.tsx", "source_location": "L160"}, {"caller_nid": "page_handleaddcontact", "callee": "alert", "source_file": "apps\\web\\src\\app\\dashboard\\customers\\page.tsx", "source_location": "L162"}, {"caller_nid": "page_handleaddcontact", "callee": "alert", "source_file": "apps\\web\\src\\app\\dashboard\\customers\\page.tsx", "source_location": "L164"}, {"caller_nid": "page_togglecustomeractivestate", "callee": "find", "source_file": "apps\\web\\src\\app\\dashboard\\customers\\page.tsx", "source_location": "L169"}, {"caller_nid": "page_togglecustomeractivestate", "callee": "patch", "source_file": "apps\\web\\src\\app\\dashboard\\customers\\page.tsx", "source_location": "L172"}, {"caller_nid": "page_togglecustomeractivestate", "callee": "alert", "source_file": "apps\\web\\src\\app\\dashboard\\customers\\page.tsx", "source_location": "L175"}, {"caller_nid": "page_handleloadtimeline", "callee": "setActiveCustId", "source_file": "apps\\web\\src\\app\\dashboard\\customers\\page.tsx", "source_location": "L180"}, {"caller_nid": "page_handleloadtimeline", "callee": "setActivePanel", "source_file": "apps\\web\\src\\app\\dashboard\\customers\\page.tsx", "source_location": "L181"}, {"caller_nid": "page_handleloadtimeline", "callee": "setSelectedTimeline", "source_file": "apps\\web\\src\\app\\dashboard\\customers\\page.tsx", "source_location": "L182"}, {"caller_nid": "page_handleloadtimeline", "callee": "get", "source_file": "apps\\web\\src\\app\\dashboard\\customers\\page.tsx", "source_location": "L184"}, {"caller_nid": "page_handleloadtimeline", "callee": "setSelectedTimeline", "source_file": "apps\\web\\src\\app\\dashboard\\customers\\page.tsx", "source_location": "L185"}, {"caller_nid": "page_handleloadtimeline", "callee": "alert", "source_file": "apps\\web\\src\\app\\dashboard\\customers\\page.tsx", "source_location": "L187"}]}